docs/conf.py
examples/auto_invoice_splitter_extraction_example.py
examples/auto_multi_receipts_extraction_example.py
examples/custom_line_items_reconstruction.py
examples/display_cropping.py
mindee/__init__.py
mindee/__main__.py
mindee/cli.py
mindee/client.py
mindee/client_mixin.py
mindee/client_v2.py
mindee/logger.py
mindee/py.typed
mindee/versions.py
mindee/commands/__init__.py
mindee/commands/cli_parser.py
mindee/commands/cli_products.py
mindee/error/__init__.py
mindee/error/geometry_error.py
mindee/error/mimetype_error.py
mindee/error/mindee_error.py
mindee/error/mindee_http_error.py
mindee/error/mindee_http_error_v2.py
mindee/error/mindee_image_error.py
mindee/error/mindee_pdf_error.py
mindee/extraction/__init__.py
mindee/extraction/common/__init__.py
mindee/extraction/common/extracted_image.py
mindee/extraction/common/image_extractor.py
mindee/extraction/multi_receipts_extractor/__init__.py
mindee/extraction/multi_receipts_extractor/multi_receipts_extractor.py
mindee/extraction/pdf_extractor/__init__.py
mindee/extraction/pdf_extractor/extracted_pdf.py
mindee/extraction/pdf_extractor/pdf_extractor.py
mindee/geometry/__init__.py
mindee/geometry/bbox.py
mindee/geometry/minmax.py
mindee/geometry/point.py
mindee/geometry/polygon.py
mindee/geometry/polygon_utils.py
mindee/geometry/quadrilateral.py
mindee/image_operations/__init__.py
mindee/image_operations/image_compressor.py
mindee/input/__init__.py
mindee/input/inference_parameters.py
mindee/input/local_response.py
mindee/input/page_options.py
mindee/input/polling_options.py
mindee/input/predict_options.py
mindee/input/workflow_options.py
mindee/input/sources/__init__.py
mindee/input/sources/base_64_input.py
mindee/input/sources/bytes_input.py
mindee/input/sources/file_input.py
mindee/input/sources/input_type.py
mindee/input/sources/local_input_source.py
mindee/input/sources/path_input.py
mindee/input/sources/url_input_source.py
mindee/mindee_http/__init__.py
mindee/mindee_http/base_endpoint.py
mindee-4.29.1.dist-info/licenses/LICENSE
mindee-4.29.1.dist-info/METADATA
mindee-4.29.1.dist-info/WHEEL
mindee-4.29.1.dist-info/entry_points.txt
mindee-4.29.1.dist-info/top_level.txt
mindee-4.29.1.dist-info/RECORD
