Metadata-Version: 2.4
Name: mindee
Version: 4.29.1
Summary: Mindee API helper library for Python
Author-email: Mindee <opensource@mindee.com>
License: MIT License
Project-URL: Homepage, https://www.mindee.com
Project-URL: Documentation, https://developers.mindee.com/docs/python-sdk
Project-URL: Repository, https://github.com/publicMindee/mindee-api-python
Project-URL: Issues, https://github.com/mindee/mindee-api-python/issues
Project-URL: Changelog, https://github.com/mindee/mindee-api-python/blob/main/CHANGELOG.md
Classifier: Programming Language :: Python :: 3
Classifier: Programming Language :: Python :: 3.8
Classifier: Programming Language :: Python :: 3.9
Classifier: Programming Language :: Python :: 3.10
Classifier: Programming Language :: Python :: 3.11
Classifier: Programming Language :: Python :: 3.12
Classifier: Programming Language :: Python :: 3.13
Classifier: Operating System :: OS Independent
Classifier: Development Status :: 5 - Production/Stable
Classifier: Intended Audience :: Developers
Classifier: Topic :: Software Development :: Libraries
Classifier: License :: OSI Approved :: MIT License
Requires-Python: >=3.8
License-File: LICENSE
Requires-Dist: pypdfium2<4.30.1,>=4.0
Requires-Dist: Pillow>=9.5.0
Requires-Dist: pytz>=2023.3
Requires-Dist: requests>=2.31.0
Provides-Extra: lint
Requires-Dist: pylint==3.3.9; extra == "lint"
Requires-Dist: pre-commit~=3.6.0; extra == "lint"
Requires-Dist: types-pytz>=2024.2; extra == "lint"
Requires-Dist: types-requests>=2.31; extra == "lint"
Provides-Extra: test
Requires-Dist: toml~=0.10.2; extra == "test"
Requires-Dist: pytest~=7.4; extra == "test"
Requires-Dist: pytest-cov~=5.0; extra == "test"
Provides-Extra: docs
Requires-Dist: sphinx~=5.3; extra == "docs"
Requires-Dist: sphinx_rtd_theme~=1.1; extra == "docs"
Requires-Dist: sphinx-autodoc-typehints~=1.20; extra == "docs"
Provides-Extra: build
Requires-Dist: build; extra == "build"
Requires-Dist: twine; extra == "build"
Dynamic: license-file
